README.md
setup.py
gwdet/__init__.py
gwdet/gwdet.py
gwdet.egg-info/PKG-INFO
gwdet.egg-info/SOURCES.txt
gwdet.egg-info/dependency_links.txt
gwdet.egg-info/not-zip-safe
gwdet.egg-info/requires.txt
gwdet.egg-info/top_level.txt