Metadata-Version: 1.1
Name: gwdet
Version: 0.1.1
Summary: Detectability of gravitational-wave signals from compact binary coalescences
Home-page: https://github.com/dgerosa/gwdet
Author: Davide Gerosa
Author-email: dgerosa@caltech.edu
License: MIT
Keywords: gravitational-wave,black-hole binary
Platform: UNKNOWN
Classifier: Topic :: Scientific/Engineering :: Astronomy
Classifier: Topic :: Scientific/Engineering :: Physics
Classifier: Topic :: Scientific/Engineering :: Mathematics
Classifier: Intended Audience :: Science/Research
Classifier: Programming Language :: Python :: 2.7
Classifier: Topic :: Software Development :: Libraries :: Python Modules
